adafruit_character_lcd/__init__.py
adafruit_character_lcd/character_lcd.py
adafruit_character_lcd/character_lcd_i2c.py
adafruit_character_lcd/character_lcd_rgb_i2c.py
adafruit_character_lcd/character_lcd_spi.py
adafruit_circuitpython_charlcd-3.5.5.dist-info/licenses/LICENSE
adafruit_circuitpython_charlcd-3.5.5.dist-info/METADATA
adafruit_circuitpython_charlcd-3.5.5.dist-info/WHEEL
adafruit_circuitpython_charlcd-3.5.5.dist-info/top_level.txt
adafruit_circuitpython_charlcd-3.5.5.dist-info/RECORD
