Metadata-Version: 2.4
Name: adafruit-circuitpython-charlcd
Version: 3.5.5
Summary: CircuitPython library for standard character LCDs.
Author-email: Adafruit Industries <circuitpython@adafruit.com>
License: MIT
Project-URL: Homepage, https://github.com/adafruit/Adafruit_CircuitPython_CharLCD
Keywords: adafruit,character,lcd,rgb,16x2,20x4,hardware,micropython,circuitpython
Classifier: Intended Audience :: Developers
Classifier: Topic :: Software Development :: Libraries
Classifier: Topic :: Software Development :: Embedded Systems
Classifier: Topic :: System :: Hardware
Classifier: License :: OSI Approved :: MIT License
Classifier: Programming Language :: Python :: 3
License-File: LICENSE
Requires-Dist: Adafruit-Blinka
Requires-Dist: adafruit-circuitpython-mcp230xx
Requires-Dist: adafruit-circuitpython-busdevice
Requires-Dist: adafruit-circuitpython-74hc595
Requires-Dist: adafruit-circuitpython-typing~=1.5
Provides-Extra: optional
Dynamic: license-file
